{
  "ledger_id": "PAPER_RESULT_LEDGER_001",
  "mode": "paper_only",
  "signal_id": "PAPER_SIGNAL_FIXTURE_001",
  "symbol": "EUR_USD_PAPER",
  "side": "long",
  "quantity": 1,
  "paper_decision": "PAPER_SIMULATED",
  "paper_result": "paper_fill_recorded",
  "paper_entry_price": 1.0848,
  "paper_exit_price": null,
  "blocked_reason": "",
  "validated_at": "2026-05-12T03:39:41Z",
  "live_execution_status": "BLOCKED",
  "broker_status": "BLOCKED",
  "oanda_status": "BLOCKED",
  "api_key_status": "BLOCKED",
  "secrets_status": "BLOCKED",
  "real_webhook_status": "BLOCKED",
  "real_order_status": "BLOCKED"
}
