{
  "default_mode": "dry_run",
  "runtime_flag": "--owner-approved-controlled-micro-live-exception",
  "broker": "OANDA",
  "environment": "live",
  "endpoint": "https://api-fxtrade.oanda.com",
  "live_item_ref": "AIOS / OANDA / Live / Broker Runtime",
  "required_allowed_mode": "controlled_micro_live_exception_only",
  "instrument": "EUR_USD",
  "units": 1,
  "side": "buy",
  "order_type": "market",
  "transport_order_type": "MARKET",
  "time_in_force": "FOK",
  "stop_loss_required": true,
  "take_profit_required": true,
  "max_orders_per_run": 1,
  "micro_live_size_policy": "minimum_owner_approved_size_only",
  "live_order_execution_by_this_packet": false,
  "demo_order_execution_by_this_packet": false,
  "money_movement_by_this_packet": false,
  "scheduler_started_by_this_packet": false,
  "daemon_started_by_this_packet": false,
  "webhook_started_by_this_packet": false,
  "next_stage_after_success": "micro_live_evidence_review"
}
